README.md
setup.py
infrasonar_selenium/__init__.py
infrasonar_selenium/base.py
infrasonar_selenium.egg-info/PKG-INFO
infrasonar_selenium.egg-info/SOURCES.txt
infrasonar_selenium.egg-info/dependency_links.txt
infrasonar_selenium.egg-info/requires.txt
infrasonar_selenium.egg-info/top_level.txt