Metadata-Version: 2.4
Name: infrasonar_selenium
Version: 1.0.1
Summary: Library for building InfraSonar Selenium tests
Home-page: https://github.com/infrasonar/selenium
Download-URL: https://github.com/infrasonar/selenium/tarball/v1.0.1
Author: Cesbit
Author-email: info@cesbit.com
Keywords: monitoring,infrasonar,agent,selenium
Classifier: Intended Audience :: Developers
Classifier: Operating System :: OS Independent
Classifier: Programming Language :: Python :: 3.9
Classifier: Programming Language :: Python :: 3.10
Classifier: Programming Language :: Python :: 3.11
Classifier: Programming Language :: Python :: 3.12
Classifier: Programming Language :: Python :: 3 :: Only
Classifier: Topic :: Software Development :: Libraries :: Python Modules
Classifier: Topic :: Text Processing :: Linguistic
Requires-Dist: selenium
Dynamic: author
Dynamic: author-email
Dynamic: classifier
Dynamic: description
Dynamic: description-content-type
Dynamic: download-url
Dynamic: home-page
Dynamic: keywords
Dynamic: requires-dist
Dynamic: summary
